wt_plus/__init__.py
wt_plus/__main__.py
wt_plus/cli/__init__.py
wt_plus/cli/db.py
wt_plus/cli/magento2.py
wt_plus/cli/services.py
wt_plus/cli/tools.py
wt_plus/cli/wt.py
wt_plus/core/__init__.py
wt_plus/core/config.py
wt_plus/core/db.py
wt_plus/core/host.py
wt_plus/core/http.py
wt_plus/core/magento2.py
wt_plus/core/mailhog.py
wt_plus/core/php.py
wt_plus/core/rabbitmq.py
wt_plus/core/redis.py
wt_plus/core/site.py
wt_plus/scripts/magento/taf-secret-token.php
wt_plus/templates/openssl.conf.jinja
wt_plus/templates/apache/virtualhost-302.conf.jinja
wt_plus/templates/apache/virtualhost.conf.jinja
wt_plus/templates/config/recaptcha_keys.json
wt_plus/templates/config/wt.yml
wt_plus/templates/magento2/env.php.jinja
wt_plus/templates/php/pool.conf.jinja
wt_plus-0.1.6a1.dist-info/LICENSE
wt_plus-0.1.6a1.dist-info/METADATA
wt_plus-0.1.6a1.dist-info/WHEEL
wt_plus-0.1.6a1.dist-info/entry_points.txt
wt_plus-0.1.6a1.dist-info/top_level.txt
wt_plus-0.1.6a1.dist-info/RECORD
