Metadata-Version: 2.1
Name: wt-plus
Version: 0.1.6a1
Summary: Development Environment
Home-page: https://wt.plus
Author: Anderson Custodio
Author-email: contato@andersoncustodio.com
License: BSD-3-Clause
Project-URL: Donate, https://wt.plus/donate
Project-URL: Documentation, https://wt.plus/
Project-URL: Changes, https://wt.plus/changes/
Project-URL: Source Code, https://github.com/andersoncustodio/wt-plus/
Project-URL: Issue Tracker, https://github.com/andersoncustodio/wt-plus/issues/
Classifier: Development Status :: 2 - Pre-Alpha
Classifier: Environment :: Web Environment
Classifier: Intended Audience :: Developers
Classifier: License :: OSI Approved :: BSD License
Classifier: Operating System :: POSIX
Classifier: Programming Language :: PHP
Requires-Python: >=3.6
License-File: LICENSE
Requires-Dist: click (==8.0)
Requires-Dist: Unidecode (>=1.3.2)
Requires-Dist: python-magic (>=0.4.24)
Requires-Dist: PyYAML (>=5.3.1)
Requires-Dist: Jinja2 (>=3.0)
Requires-Dist: setuptools (>=45.2.0)
Requires-Dist: PyMySQL (>=1.0.2)
Requires-Dist: packaging (>=20.9)
Requires-Dist: prettytable (>=2.2.0)
Requires-Dist: ruamel.yaml (>=0.17.1)
